understand/__init__.py
understand/main.py
Understand-0.0.3.dist-info/METADATA
Understand-0.0.3.dist-info/WHEEL
Understand-0.0.3.dist-info/top_level.txt
Understand-0.0.3.dist-info/RECORD
