Metadata-Version: 2.1
Name: Understand
Version: 0.0.3
Summary: A package to detect intent from text based on training.
Home-page: https://github.com/Ulto85/horoscope
Author: Robowolf
Author-email: ultoulto4@gmail.com
License: UNKNOWN
Project-URL: Bug Tracker, https://github.com/Ulto85/horoscope/issues
Platform: UNKNOWN
Classifier: Programming Language :: Python :: 3
Classifier: License :: OSI Approved :: MIT License
Classifier: Operating System :: OS Independent
Requires-Python: >=3.6
